django_dragonpay/__init__.py
django_dragonpay/admin.py
django_dragonpay/constants.py
django_dragonpay/exceptions.py
django_dragonpay/forms.py
django_dragonpay/models.py
django_dragonpay/settings.py
django_dragonpay/urls.py
django_dragonpay/utils.py
django_dragonpay/views.py
django_dragonpay/api/__init__.py
django_dragonpay/api/http_get.py
django_dragonpay/api/soap.py
django_dragonpay/migrations/0001_initial.py
django_dragonpay/migrations/0002_transaction_status_options.py
django_dragonpay/migrations/0003_larger_max_length.py
django_dragonpay/migrations/__init__.py
django_dragonpay/templates/.DS_Store
django_dragonpay/templates/dragonpay_soapxml/CancelTransaction.xml
django_dragonpay/templates/dragonpay_soapxml/GetAvailableProcessors.xml
django_dragonpay/templates/dragonpay_soapxml/GetPayoutData.xml
django_dragonpay/templates/dragonpay_soapxml/GetPayoutTxnStatus.xml
django_dragonpay/templates/dragonpay_soapxml/GetTxnToken.xml
django_dragonpay/templates/dragonpay_soapxml/ModifyPayoutChannel.xml
django_dragonpay/templates/dragonpay_soapxml/RegisterPayoutUser.xml
django_dragonpay/templates/dragonpay_soapxml/RequestMultiplePayouts.xml
django_dragonpay/templates/dragonpay_soapxml/RequestPayout.xml
django_dragonpay/templates/dragonpay_soapxml/RequestPayoutEx.xml
django_dragonpay/templates/dragonpay_soapxml/base.xml
django_dragonpay/templates/dragonpay_soapxml/send_billing_info.xml
django_dragonpay/templates/dragonpay_soapxml/webmethod.xml
django_dragonpay-0.1.9.dist-info/DESCRIPTION.rst
django_dragonpay-0.1.9.dist-info/METADATA
django_dragonpay-0.1.9.dist-info/RECORD
django_dragonpay-0.1.9.dist-info/WHEEL
django_dragonpay-0.1.9.dist-info/metadata.json
django_dragonpay-0.1.9.dist-info/top_level.txt
