Metadata-Version: 2.0
Name: django-dragonpay
Version: 0.1.9
Summary: DragonPay plugin for Django
Home-page: https://github.com/ibaguio/django_dragonpay
Author: Ivan Dominic Baguio
Author-email: baguio.ivan@gmail.com
License: MIT
Keywords: django dragonpay payment
Platform: UNKNOWN
Requires-Dist: requests (>=2.11.1)
Requires-Dist: Django (>=1.8.0)
Requires-Dist: lxml (==3.7.3)
Requires-Dist: pycrypto (>=2.6.1)
